jiushu_logger_flask/__init__.py
jiushu_logger_flask/route_logging.py
jiushu_logger_flask-1.0.2.dist-info/LICENSE
jiushu_logger_flask-1.0.2.dist-info/WHEEL
jiushu_logger_flask-1.0.2.dist-info/METADATA
jiushu_logger_flask-1.0.2.dist-info/RECORD
