Metadata-Version: 2.1
Name: jiushu_logger_flask
Version: 1.0.2
Summary: Jiushu logger for Flask routes.
Author-email: Ai Tutu <zhixiao.yang0124@gmail.com>
Requires-Python: >=3.7
Classifier: License :: OSI Approved :: The Unlicense (Unlicense)
Classifier: Operating System :: OS Independent
Classifier: Programming Language :: Python :: 3
Classifier: Topic :: System :: Logging
Classifier: Typing :: Typed
Requires-Dist: flask >=2.0.0
Requires-Dist: jiushu-logger >=1.0.4
Requires-Dist: orjson >=3.8.0
Requires-Dist: python-ulid >=1.1.0
Requires-Dist: flask-unittest ; extra == "test"
Project-URL: Bug Tracker, https://github.com/XiaoxiaFamily/jiushu-logger-flask/issues
Project-URL: Homepage, https://github.com/XiaoxiaFamily/jiushu-logger-flask
Provides-Extra: test
